datacooker/__init__.py
datacooker/recipes/__init__.py
datacooker/recipes/auto_regressive_recipe.py
datacooker/recipes/logit_recipe.py
datacooker/recipes/poisson_recipe.py
datacooker/recipes/recipe.py
datacooker/utils/__init__.py
datacooker/utils/is_valid_fraction.py
datacooker/variables/__init__.py
datacooker/variables/continous_variable.py
datacooker/variables/discrete_variable.py
datacooker/variables/error_messages.py
datacooker/variables/nominal_variable.py
datacooker/variables/variable.py
datacooker-0.4.1.dist-info/LICENSE
datacooker-0.4.1.dist-info/METADATA
datacooker-0.4.1.dist-info/WHEEL
datacooker-0.4.1.dist-info/RECORD
