Metadata-Version: 2.1
Name: datacooker
Version: 0.4.1
Summary: Library for data generation based on model specs (Recipes)
License: MIT
Author: Guilherme
Author-email: g.lisboa.oliveira@outlook.com
Requires-Python: >=3.10,<3.12
Classifier: License :: OSI Approved :: MIT License
Classifier: Programming Language :: Python :: 3
Classifier: Programming Language :: Python :: 3.10
Classifier: Programming Language :: Python :: 3.11
Requires-Dist: numpy (>=1.23.4,<2.0.0)
Requires-Dist: pandas (>=2.0.1,<3.0.0)
Requires-Dist: scipy (>=1.9.2,<2.0.0)
